stablefusion/Home.py
stablefusion/__init__.py
stablefusion/model_list.txt
stablefusion/utils.py
stablefusion/api/__init__.py
stablefusion/api/main.py
stablefusion/api/schemas.py
stablefusion/api/utils.py
stablefusion/cli/__init__.py
stablefusion/cli/main.py
stablefusion/cli/run_api.py
stablefusion/cli/run_app.py
stablefusion/data/artists.txt
stablefusion/data/flavors.txt
stablefusion/data/mediums.txt
stablefusion/data/movements.txt
stablefusion/models/ckpt_interference/t
stablefusion/models/cpkt_models/t
stablefusion/models/diffusion_models/t.txt
stablefusion/models/realesrgan/inference_realesrgan.py
stablefusion/models/realesrgan/options/finetune_realesrgan_x4plus.yml
stablefusion/models/realesrgan/options/finetune_realesrgan_x4plus_pairdata.yml
stablefusion/models/realesrgan/options/train_realesrgan_x2plus.yml
stablefusion/models/realesrgan/options/train_realesrgan_x4plus.yml
stablefusion/models/realesrgan/options/train_realesrnet_x2plus.yml
stablefusion/models/realesrgan/options/train_realesrnet_x4plus.yml
stablefusion/models/realesrgan/realesrgan/__init__.py
stablefusion/models/realesrgan/realesrgan/train.py
stablefusion/models/realesrgan/realesrgan/utils.py
stablefusion/models/realesrgan/realesrgan/archs/__init__.py
stablefusion/models/realesrgan/realesrgan/archs/discriminator_arch.py
stablefusion/models/realesrgan/realesrgan/archs/srvgg_arch.py
stablefusion/models/realesrgan/realesrgan/data/__init__.py
stablefusion/models/realesrgan/realesrgan/data/realesrgan_dataset.py
stablefusion/models/realesrgan/realesrgan/data/realesrgan_paired_dataset.py
stablefusion/models/realesrgan/realesrgan/models/__init__.py
stablefusion/models/realesrgan/realesrgan/models/realesrgan_model.py
stablefusion/models/realesrgan/realesrgan/models/realesrnet_model.py
stablefusion/models/realesrgan/weights/README.md
stablefusion/models/safetensors_models/t
stablefusion/pages/10_Utilities.py
stablefusion/pages/1_Text2Image.py
stablefusion/pages/2_Image2Image.py
stablefusion-0.1.4.dist-info/LICENSE
stablefusion-0.1.4.dist-info/METADATA
stablefusion-0.1.4.dist-info/WHEEL
stablefusion-0.1.4.dist-info/entry_points.txt
stablefusion-0.1.4.dist-info/top_level.txt
stablefusion-0.1.4.dist-info/RECORD
