Metadata-Version: 2.1
Name: stablefusion
Version: 0.1.4
Summary: StableFusion
Home-page: https://github.com/NeuralRealm/StableFusion
Author: NeuralRealm
Keywords: stablefusion
Classifier: Intended Audience :: Developers
Classifier: Intended Audience :: Education
Classifier: Intended Audience :: Science/Research
Classifier: License :: OSI Approved :: Apache Software License
Classifier: Operating System :: OS Independent
Classifier: Programming Language :: Python :: 3.8
Classifier: Programming Language :: Python :: 3.9
Classifier: Programming Language :: Python :: 3.10
Classifier: Topic :: Scientific/Engineering :: Artificial Intelligence
Requires-Python: >=3.7
License-File: LICENSE
Requires-Dist: accelerate (==0.15.0)
Requires-Dist: basicsr (>=1.4.2)
Requires-Dist: diffusers (>=0.14.0)
Requires-Dist: facexlib (>=0.2.5)
Requires-Dist: fairscale (==0.4.4)
Requires-Dist: fastapi (==0.88.0)
Requires-Dist: gfpgan (>=1.3.7)
Requires-Dist: huggingface-hub (>=0.11.1)
Requires-Dist: loguru (==0.6.0)
Requires-Dist: open-clip-torch (==2.9.1)
Requires-Dist: opencv-python
Requires-Dist: protobuf (==3.20)
Requires-Dist: pyngrok (==5.2.1)
Requires-Dist: python-multipart (==0.0.5)
Requires-Dist: realesrgan (>=0.2.5)
Requires-Dist: streamlit (==1.16.0)
Requires-Dist: streamlit-drawable-canvas (==0.9.0)
Requires-Dist: st-clickable-images (==0.0.3)
Requires-Dist: timm (==0.4.12)
Requires-Dist: torch (>=1.12.0)
Requires-Dist: torchvision (>=0.13.0)
Requires-Dist: transformers (==4.25.1)
Requires-Dist: uvicorn (==0.15.0)
Requires-Dist: OmegaConf
Requires-Dist: tqdl
Requires-Dist: xformers
Requires-Dist: bitsandbytes
Requires-Dist: safetensors
Requires-Dist: controlnet-aux
Provides-Extra: dev
Requires-Dist: black (~=22.0) ; extra == 'dev'
Requires-Dist: isort (==5.8.0) ; extra == 'dev'
Requires-Dist: flake8 (==3.9.2) ; extra == 'dev'
Requires-Dist: mypy (==0.901) ; extra == 'dev'
Provides-Extra: docs
Requires-Dist: recommonmark ; extra == 'docs'
Requires-Dist: sphinx (==3.1.2) ; extra == 'docs'
Requires-Dist: sphinx-markdown-tables ; extra == 'docs'
Requires-Dist: sphinx-rtd-theme (==0.4.3) ; extra == 'docs'
Requires-Dist: sphinx-copybutton ; extra == 'docs'
Provides-Extra: quality
Requires-Dist: black (~=22.0) ; extra == 'quality'
Requires-Dist: isort (==5.8.0) ; extra == 'quality'
Requires-Dist: flake8 (==3.9.2) ; extra == 'quality'
Requires-Dist: mypy (==0.901) ; extra == 'quality'
Provides-Extra: test
Requires-Dist: pytest ; extra == 'test'
Requires-Dist: pytest-cov ; extra == 'test'
